coredb_pgmq_python/__init__.py
coredb_pgmq_python/queue.py
coredb_pgmq_python-0.2.2.dist-info/WHEEL
coredb_pgmq_python-0.2.2.dist-info/METADATA
coredb_pgmq_python-0.2.2.dist-info/RECORD
