Metadata-Version: 2.1
Name: coredb-pgmq-python
Version: 0.2.2
Summary: Python client for the PGMQ Postgres extension.
License: Apache 2.0
Author: Adam Hendel
Author-email: adam@coredb.io
Requires-Python: >=3.9,<4.0
Classifier: License :: Other/Proprietary License
Classifier: Programming Language :: Python :: 3
Classifier: Programming Language :: Python :: 3.9
Classifier: Programming Language :: Python :: 3.10
Classifier: Programming Language :: Python :: 3.11
Requires-Dist: orjson (>=3.8.10,<4.0.0)
Requires-Dist: psycopg[binary,pool] (>=3.1.8,<4.0.0)
Requires-Dist: pydantic (>=1.10.7,<2.0.0)
Project-URL: Documentation, https://github.com/CoreDB-io/coredb/tree/main/pgmq/coredb-pgmq-python
Project-URL: Homepage, https://github.com/CoreDB-io/coredb
Project-URL: Repository, https://github.com/CoreDB-io/coredb/tree/main/pgmq/coredb-pgmq-python
